Metadata-Version: 2.1
Name: choirless-smiler
Version: 1.2.1
Summary: A library and command to extract the smiliest image from a video
Home-page: https://github.com/choirless/smiler
Author: Matt Hamilton
Author-email: mh@quernus.co.uk
License: UNKNOWN
Platform: UNKNOWN
Classifier: Programming Language :: Python :: 3
Classifier: License :: OSI Approved :: MIT License
Classifier: Operating System :: OS Independent
Requires-Python: >=3.6
